docker/scripts/main.py
docker/scripts/roles/index.py
docs/conf.py
magnet/__init__.py
magnet/base.py
magnet/ic/__init__.py
magnet/ic/field.py
magnet/ize/__init__.py
magnet/ize/memory.py
magnet/ron/__init__.py
magnet/ron/llm.py
magnet/utils/__init__.py
magnet/utils/data_classes.py
magnet/utils/globals.py
magnet/utils/nats.py
magnet/utils/index/milvus.py
magnet/utils/llm/api.py
magnet/utils/llm/local.py
magnet/utils/llm/prompts.py
magnet/utils/mlx/__init__.py
magnet/utils/mlx/mistral.py
tests/test_Prism.py
llm_magnet-0.3.17.dist-info/LICENSE
llm_magnet-0.3.17.dist-info/METADATA
llm_magnet-0.3.17.dist-info/WHEEL
llm_magnet-0.3.17.dist-info/top_level.txt
llm_magnet-0.3.17.dist-info/RECORD
