Metadata-Version: 2.1
Name: llm_magnet
Version: 0.3.17
Summary: the small distributed language model toolkit. fine-tune state-of-the-art LLMs anywhere, rapidly.
Home-page: https://github.com/Prismadic/magnet
License-File: LICENSE
